graphite-paper/__init__.py
graphite_paper/__init__.py
graphite_paper/horst/__init__.py
graphite_paper/horst/asides.py
graphite_paper/horst/entries.py
graphite_paper/horst/helper.py
graphite_paper/horst/inlines.py
graphite_paper/horst/jinja2.py
graphite_paper/horst/parser.py
graphite_paper/horst/plugins.py
graphite_paper/horst/render.py
graphite_paper/horst/report.py
graphite_paper/jinja2/__init__.py
graphite_paper/jinja2/base.html
graphite_paper/jinja2/nav.html
graphite_paper/jinja2/horst/__init__.py
graphite_paper/jinja2/horst/article_top.html
graphite_paper/jinja2/horst/footer.html
graphite_paper/jinja2/horst/frame.html
graphite_paper/jinja2/horst/jumbo.html
graphite_paper/jinja2/horst/meta.html
graphite_paper/jinja2/horst/report.html
graphite_paper/jinja2/horst/share.html
graphite_paper/jinja2/horst/tab_content.html
graphite_paper/jinja2/horst/plugins/__init__.py
graphite_paper/jinja2/horst/plugins/article_top.html
graphite_paper/jinja2/horst/plugins/article_top_aside.html
graphite_paper/jinja2/horst/plugins/author.html
graphite_paper/jinja2/horst/plugins/author_aside.html
graphite_paper/jinja2/horst/plugins/author_pre.html
graphite_paper/jinja2/horst/plugins/chapter_header.html
graphite_paper/jinja2/horst/plugins/figure.html
graphite_paper/jinja2/horst/plugins/figure_aside.html
graphite_paper/jinja2/horst/plugins/infobox.html
graphite_paper/jinja2/horst/plugins/infobox_aside.html
graphite_paper/jinja2/horst/plugins/listof_aside.html
graphite_paper/jinja2/horst/plugins/listoffigures.html
graphite_paper/jinja2/horst/plugins/listofreferences.html
graphite_paper/jinja2/horst/plugins/quote.html
graphite_paper/jinja2/horst/plugins/quote_aside.html
graphite_paper/jinja2/horst/plugins/slides.html
graphite_paper/jinja2/horst/plugins/table.html
graphite_paper/jinja2/horst/plugins/table_aside.html
graphite_paper/jinja2/horst/plugins/variable.html
graphite_paper/jinja2/horst/plugins/variable_aside.html
graphite_paper/jinja2/horst/plugins/video.html
graphite_paper-0.0.6.dist-info/METADATA
graphite_paper-0.0.6.dist-info/WHEEL
graphite_paper-0.0.6.dist-info/top_level.txt
graphite_paper-0.0.6.dist-info/RECORD
