Metadata-Version: 2.1
Name: graphite-paper
Version: 0.0.6
Summary: Graphite Paper
Home-page: http://www.impactdistillery.com/graphite
Author: Larissa Wunderlich and Marcel Hebing
Author-email: info@impactdistillery.com
License: None
Platform: UNKNOWN
Requires-Python: >=3.6
Requires-Dist: Django
Requires-Dist: Jinja2
Requires-Dist: Markdown
Requires-Dist: MarkupSafe
Requires-Dist: numpy
Requires-Dist: pandas
Requires-Dist: python-dateutil
Requires-Dist: pytz
Requires-Dist: PyYAML
Requires-Dist: six
